schr/__init__.py
schr/core/__init__.py
schr/core/base.py
schr/py.typed
schr/qed/__init__.py
schr/qed/field.py
schr/qed/interaction.py
schr/qm/__init__.py
schr/qm/hamiltonian.py
schr/qm/solvers.py
schr/qm/wavefunction.py
schr/utils/__init__.py
schr/utils/absorbing_boundary.py
schr/utils/fft.py
schr/utils/grid.py
schr/utils/paths.py
schr/utils/visualization.py
schr-0.1.0.dist-info/WHEEL
schr-0.1.0.dist-info/METADATA
schr-0.1.0.dist-info/RECORD
