Metadata-Version: 2.3
Name: schr
Version: 0.1.0
Summary: Schr: GPU-Accelerated Quantum Mechanics and QED Simulator
Keywords: quantum mechanics,quantum electrodynamics,JAX,GPU,simulation,physics
Author: sql-hkr
Author-email: sql-hkr <sql.hkr@gmail.com>
Classifier: Development Status :: 3 - Alpha
Classifier: Intended Audience :: Science/Research
Classifier: License :: OSI Approved :: MIT License
Classifier: Programming Language :: Python :: 3
Classifier: Programming Language :: Python :: 3.11
Classifier: Programming Language :: Python :: 3.12
Classifier: Programming Language :: Python :: 3.13
Classifier: Topic :: Scientific/Engineering :: Physics
Requires-Dist: jax>=0.8.0
Requires-Dist: jaxlib>=0.8.0
Requires-Dist: matplotlib>=3.10.7
Requires-Dist: tqdm>=4.67.1
Requires-Python: >=3.11
Project-URL: Documentation, https://github.com/sql-hkr/schr/blob/main/README.md
Project-URL: Homepage, https://github.com/sql-hkr/schr
Project-URL: Issues, https://github.com/sql-hkr/schr/issues
Project-URL: Repository, https://github.com/sql-hkr/schr
